udsonip/__init__.py
udsonip/client.py
udsonip/connection.py
udsonip/constants.py
udsonip/discovery.py
udsonip/exceptions.py
udsonip/manager.py
udsonip-0.4.0.dist-info/licenses/LICENSE
udsonip-0.4.0.dist-info/METADATA
udsonip-0.4.0.dist-info/WHEEL
udsonip-0.4.0.dist-info/top_level.txt
udsonip-0.4.0.dist-info/RECORD
