Metadata-Version: 2.4
Name: udsonip
Version: 0.4.0
Summary: Enhanced UDS-on-IP integration library providing seamless multi-ECU support
Author-email: Sirius Wu <ccwu660601@gmail.com>
License: MIT
Project-URL: Homepage, https://github.com/sirius-cc-wu/python-udsonip
Project-URL: Documentation, https://python-udsonip.readthedocs.io
Project-URL: Repository, https://github.com/sirius-cc-wu/python-udsonip
Project-URL: Issues, https://github.com/sirius-cc-wu/python-udsonip/issues
Keywords: doip,uds,automotive,diagnostics,iso13400,iso14229
Classifier: Development Status :: 3 - Alpha
Classifier: Intended Audience :: Developers
Classifier: License :: OSI Approved :: MIT License
Classifier: Programming Language :: Python :: 3
Classifier: Programming Language :: Python :: 3.7
Classifier: Programming Language :: Python :: 3.8
Classifier: Programming Language :: Python :: 3.9
Classifier: Programming Language :: Python :: 3.10
Classifier: Programming Language :: Python :: 3.11
Classifier: Topic :: Software Development :: Libraries :: Python Modules
Classifier: Topic :: System :: Hardware :: Hardware Drivers
Requires-Python: >=3.7
License-File: LICENSE
Requires-Dist: doipclient>=1.1.7
Requires-Dist: udsoncan>=1.21
Provides-Extra: dev
Requires-Dist: pytest>=7.0; extra == "dev"
Requires-Dist: pytest-cov>=3.0; extra == "dev"
Requires-Dist: black>=22.0; extra == "dev"
Requires-Dist: flake8>=4.0; extra == "dev"
Requires-Dist: mypy>=0.950; extra == "dev"
Provides-Extra: docs
Requires-Dist: sphinx>=4.0; extra == "docs"
Requires-Dist: sphinx-rtd-theme>=1.0; extra == "docs"
Dynamic: license-file
